driveconnect/__init__.py
driveconnect/main.py
driveconnect-0.1.15.dist-info/WHEEL
driveconnect-0.1.15.dist-info/METADATA
driveconnect-0.1.15.dist-info/RECORD
